{"generated":"2026-06-30 15:02:47 UTC","lookback":50,"pivot_mode":"highest","swing":7,"risk_score":{"above_count":6,"total":8,"signal":"🟢 STRONG RISK ON","details":["SPY: Above 50 MA ✓","HYG: Above 50 MA ✓","QQQ: Above 50 MA ✓","TLT: Above 50 MA ✓","GLD: Below 50 MA ✗","IWM: Above 50 MA ✓","BTC: Below 50 MA ✗","SMH: Above 50 MA ✓"]},"pairs":[{"id":"spy-hyg","trend1":"LH + HL →","trend2":"LH + HL →","signal":"ALIGNED →→","pivots1":[{"time":1776729600,"price":704.08,"label":"LL"},{"time":1776816000,"price":711.21,"label":"HH"},{"time":1776902400,"price":708.45,"label":"HL"},{"time":1777248000,"price":715.17,"label":"HH"},{"time":1777420800,"price":711.58,"label":"HL"},{"time":1777593600,"price":720.65,"label":"HH"},{"time":1777852800,"price":718.01,"label":"HL"},{"time":1778025600,"price":733.83,"label":"HH"},{"time":1778112000,"price":731.58,"label":"HL"},{"time":1778457600,"price":739.3,"label":"HH"},{"time":1778544000,"price":738.18,"label":"HL"},{"time":1778716800,"price":748.17,"label":"HH"},{"time":1779148800,"price":733.73,"label":"HL"},{"time":1779753600,"price":750.59,"label":"HH"},{"time":1779840000,"price":750.46,"label":"HL"},{"time":1780358400,"price":759.57,"label":"HH"},{"time":1780444800,"price":754.24,"label":"HL"},{"time":1780531200,"price":757.09,"label":"LH"},{"time":1780617600,"price":735.6548,"label":"HL"},{"time":1780876800,"price":737.3204,"label":"LH"},{"time":1781049600,"price":723.5659,"label":"HL"},{"time":1781481600,"price":752.8904,"label":"LH"},{"time":1781654400,"price":739.056,"label":"HL"},{"time":1781740800,"price":746.74,"label":"LH"},{"time":1782259200,"price":733.24,"label":"HL"},{"time":1782345600,"price":734.3,"label":"LH"},{"time":1782432000,"price":728.99,"label":"HL"}],"pivots2":[{"time":1776729600,"price":80.37,"label":"LL"},{"time":1776816000,"price":80.5,"label":"LH"},{"time":1776902400,"price":80.37,"label":"HL"},{"time":1777248000,"price":80.51,"label":"LH"},{"time":1777420800,"price":80.13,"label":"LL"},{"time":1777507200,"price":80.38,"label":"LH"},{"time":1777852800,"price":79.8,"label":"LL"},{"time":1778025600,"price":80.16,"label":"LH"},{"time":1778112000,"price":79.86,"label":"HL"},{"time":1778198400,"price":80.14,"label":"LH"},{"time":1778544000,"price":79.87,"label":"HL"},{"time":1778630400,"price":79.91,"label":"LH"},{"time":1778803200,"price":79.46,"label":"LL"},{"time":1779062400,"price":79.54,"label":"LH"},{"time":1779148800,"price":79.35,"label":"LL"},{"time":1779753600,"price":80.18,"label":"LH"},{"time":1779840000,"price":80.13,"label":"HL"},{"time":1780012800,"price":80.31,"label":"LH"},{"time":1780272000,"price":79.84,"label":"HL"},{"time":1780358400,"price":79.9,"label":"LH"},{"time":1780444800,"price":79.68,"label":"HL"},{"time":1780531200,"price":79.83,"label":"LH"},{"time":1780617600,"price":79.43,"label":"HL"},{"time":1780963200,"price":79.62,"label":"LH"},{"time":1781049600,"price":79.47,"label":"HL"},{"time":1781481600,"price":80.04,"label":"LH"},{"time":1781654400,"price":79.73,"label":"HL"},{"time":1781740800,"price":80.01,"label":"LH"},{"time":1782259200,"price":79.85,"label":"HL"},{"time":1782345600,"price":79.88,"label":"LH"},{"time":1782432000,"price":79.83,"label":"HL"},{"time":1782691200,"price":80.01,"label":"LH"}]},{"id":"spy-qqq","trend1":"LH + HL →","trend2":"LH + HL →","signal":"ALIGNED →→","pivots1":[{"time":1776729600,"price":704.08,"label":"LL"},{"time":1776816000,"price":711.21,"label":"HH"},{"time":1776902400,"price":708.45,"label":"HL"},{"time":1777248000,"price":715.17,"label":"HH"},{"time":1777420800,"price":711.58,"label":"HL"},{"time":1777593600,"price":720.65,"label":"HH"},{"time":1777852800,"price":718.01,"label":"HL"},{"time":1778025600,"price":733.83,"label":"HH"},{"time":1778112000,"price":731.58,"label":"HL"},{"time":1778457600,"price":739.3,"label":"HH"},{"time":1778544000,"price":738.18,"label":"HL"},{"time":1778716800,"price":748.17,"label":"HH"},{"time":1779148800,"price":733.73,"label":"HL"},{"time":1779753600,"price":750.59,"label":"HH"},{"time":1779840000,"price":750.46,"label":"HL"},{"time":1780358400,"price":759.57,"label":"HH"},{"time":1780444800,"price":754.24,"label":"HL"},{"time":1780531200,"price":757.09,"label":"LH"},{"time":1780617600,"price":735.6548,"label":"HL"},{"time":1780876800,"price":737.3204,"label":"LH"},{"time":1781049600,"price":723.5659,"label":"HL"},{"time":1781481600,"price":752.8904,"label":"LH"},{"time":1781654400,"price":739.056,"label":"HL"},{"time":1781740800,"price":746.74,"label":"LH"},{"time":1782259200,"price":733.24,"label":"HL"},{"time":1782345600,"price":734.3,"label":"LH"},{"time":1782432000,"price":728.99,"label":"HL"}],"pivots2":[{"time":1776729600,"price":644.33,"label":"LL"},{"time":1776816000,"price":655.11,"label":"HH"},{"time":1776902400,"price":651.42,"label":"HL"},{"time":1777248000,"price":664.23,"label":"HH"},{"time":1777334400,"price":657.55,"label":"HL"},{"time":1777593600,"price":674.15,"label":"HH"},{"time":1777852800,"price":672.88,"label":"HL"},{"time":1778025600,"price":695.77,"label":"HH"},{"time":1778112000,"price":694.94,"label":"HL"},{"time":1778457600,"price":713.29,"label":"HH"},{"time":1778544000,"price":707.24,"label":"HL"},{"time":1778716800,"price":719.79,"label":"HH"},{"time":1779148800,"price":701.53,"label":"HL"},{"time":1779753600,"price":730.28,"label":"HH"},{"time":1779840000,"price":729.45,"label":"HL"},{"time":1780358400,"price":746.16,"label":"HH"},{"time":1780617600,"price":704.286,"label":"HL"},{"time":1780876800,"price":715.2839,"label":"LH"},{"time":1781049600,"price":692.9285,"label":"HL"},{"time":1781481600,"price":743.1833,"label":"LH"},{"time":1781654400,"price":721.7169,"label":"HL"},{"time":1781740800,"price":739.807,"label":"LH"},{"time":1782259200,"price":710.62,"label":"HL"},{"time":1782345600,"price":716.38,"label":"LH"},{"time":1782432000,"price":706.52,"label":"HL"}]},{"id":"spy-iwm","trend1":"LH + HL →","trend2":"HH + HL ↗","signal":"⚠️ BULLISH →↗","pivots1":[{"time":1776729600,"price":704.08,"label":"LL"},{"time":1776816000,"price":711.21,"label":"HH"},{"time":1776902400,"price":708.45,"label":"HL"},{"time":1777248000,"price":715.17,"label":"HH"},{"time":1777420800,"price":711.58,"label":"HL"},{"time":1777593600,"price":720.65,"label":"HH"},{"time":1777852800,"price":718.01,"label":"HL"},{"time":1778025600,"price":733.83,"label":"HH"},{"time":1778112000,"price":731.58,"label":"HL"},{"time":1778457600,"price":739.3,"label":"HH"},{"time":1778544000,"price":738.18,"label":"HL"},{"time":1778716800,"price":748.17,"label":"HH"},{"time":1779148800,"price":733.73,"label":"HL"},{"time":1779753600,"price":750.59,"label":"HH"},{"time":1779840000,"price":750.46,"label":"HL"},{"time":1780358400,"price":759.57,"label":"HH"},{"time":1780444800,"price":754.24,"label":"HL"},{"time":1780531200,"price":757.09,"label":"LH"},{"time":1780617600,"price":735.6548,"label":"HL"},{"time":1780876800,"price":737.3204,"label":"LH"},{"time":1781049600,"price":723.5659,"label":"HL"},{"time":1781481600,"price":752.8904,"label":"LH"},{"time":1781654400,"price":739.056,"label":"HL"},{"time":1781740800,"price":746.74,"label":"LH"},{"time":1782259200,"price":733.24,"label":"HL"},{"time":1782345600,"price":734.3,"label":"LH"},{"time":1782432000,"price":728.99,"label":"HL"}],"pivots2":[{"time":1776729600,"price":274.51,"label":"LL"},{"time":1776816000,"price":276.48,"label":"LH"},{"time":1776902400,"price":275.52,"label":"HL"},{"time":1777248000,"price":277.14,"label":"LH"},{"time":1777420800,"price":272.08,"label":"LL"},{"time":1777593600,"price":279.28,"label":"HH"},{"time":1777852800,"price":277.88,"label":"HL"},{"time":1778025600,"price":286.8,"label":"HH"},{"time":1778112000,"price":282.26,"label":"HL"},{"time":1778457600,"price":285.33,"label":"LH"},{"time":1778544000,"price":282.57,"label":"HL"},{"time":1778716800,"price":284.45,"label":"LH"},{"time":1779148800,"price":273.0,"label":"HL"},{"time":1779753600,"price":290.51,"label":"HH"},{"time":1779840000,"price":290.37,"label":"HL"},{"time":1779926400,"price":292.03,"label":"HH"},{"time":1780272000,"price":288.98,"label":"HL"},{"time":1780358400,"price":291.66,"label":"LH"},{"time":1780444800,"price":287.67,"label":"HL"},{"time":1780531200,"price":292.01,"label":"LH"},{"time":1780617600,"price":280.9818,"label":"HL"},{"time":1780963200,"price":284.3438,"label":"LH"},{"time":1781049600,"price":281.3808,"label":"HL"},{"time":1781481600,"price":294.64,"label":"HH"},{"time":1781654400,"price":289.88,"label":"HL"},{"time":1782086400,"price":298.18,"label":"HH"},{"time":1782172800,"price":295.32,"label":"HL"},{"time":1782432000,"price":299.83,"label":"HH"},{"time":1782691200,"price":298.97,"label":"HL"}]},{"id":"spy-smh","trend1":"LH + HL →","trend2":"LH + HL →","signal":"ALIGNED →→","pivots1":[{"time":1776729600,"price":704.08,"label":"LL"},{"time":1776816000,"price":711.21,"label":"HH"},{"time":1776902400,"price":708.45,"label":"HL"},{"time":1777248000,"price":715.17,"label":"HH"},{"time":1777420800,"price":711.58,"label":"HL"},{"time":1777593600,"price":720.65,"label":"HH"},{"time":1777852800,"price":718.01,"label":"HL"},{"time":1778025600,"price":733.83,"label":"HH"},{"time":1778112000,"price":731.58,"label":"HL"},{"time":1778457600,"price":739.3,"label":"HH"},{"time":1778544000,"price":738.18,"label":"HL"},{"time":1778716800,"price":748.17,"label":"HH"},{"time":1779148800,"price":733.73,"label":"HL"},{"time":1779753600,"price":750.59,"label":"HH"},{"time":1779840000,"price":750.46,"label":"HL"},{"time":1780358400,"price":759.57,"label":"HH"},{"time":1780444800,"price":754.24,"label":"HL"},{"time":1780531200,"price":757.09,"label":"LH"},{"time":1780617600,"price":735.6548,"label":"HL"},{"time":1780876800,"price":737.3204,"label":"LH"},{"time":1781049600,"price":723.5659,"label":"HL"},{"time":1781481600,"price":752.8904,"label":"LH"},{"time":1781654400,"price":739.056,"label":"HL"},{"time":1781740800,"price":746.74,"label":"LH"},{"time":1782259200,"price":733.24,"label":"HL"},{"time":1782345600,"price":734.3,"label":"LH"},{"time":1782432000,"price":728.99,"label":"HL"}],"pivots2":[{"time":1776988800,"price":506.44,"label":"HH"},{"time":1777334400,"price":491.21,"label":"HL"},{"time":1777593600,"price":509.82,"label":"HH"},{"time":1777852800,"price":506.79,"label":"HL"},{"time":1778025600,"price":549.76,"label":"HH"},{"time":1778112000,"price":540.1,"label":"HL"},{"time":1778457600,"price":576.31,"label":"HH"},{"time":1778544000,"price":561.25,"label":"HL"},{"time":1778716800,"price":578.34,"label":"HH"},{"time":1779148800,"price":543.96,"label":"HL"},{"time":1779753600,"price":602.14,"label":"HH"},{"time":1779840000,"price":595.5,"label":"HL"},{"time":1779926400,"price":599.83,"label":"LH"},{"time":1780012800,"price":598.93,"label":"HL"},{"time":1780444800,"price":637.9,"label":"HH"},{"time":1780617600,"price":569.69,"label":"HL"},{"time":1780876800,"price":598.16,"label":"LH"},{"time":1781049600,"price":570.91,"label":"HL"},{"time":1781481600,"price":647.1,"label":"HH"},{"time":1781568000,"price":616.0,"label":"HL"},{"time":1782086400,"price":668.91,"label":"HH"},{"time":1782259200,"price":618.92,"label":"HL"},{"time":1782345600,"price":636.88,"label":"LH"},{"time":1782432000,"price":611.61,"label":"HL"}]},{"id":"spy-gld","trend1":"LH + HL →","trend2":"LH + HL →","signal":"ALIGNED →→","pivots1":[{"time":1776729600,"price":704.08,"label":"LL"},{"time":1776816000,"price":711.21,"label":"HH"},{"time":1776902400,"price":708.45,"label":"HL"},{"time":1777248000,"price":715.17,"label":"HH"},{"time":1777420800,"price":711.58,"label":"HL"},{"time":1777593600,"price":720.65,"label":"HH"},{"time":1777852800,"price":718.01,"label":"HL"},{"time":1778025600,"price":733.83,"label":"HH"},{"time":1778112000,"price":731.58,"label":"HL"},{"time":1778457600,"price":739.3,"label":"HH"},{"time":1778544000,"price":738.18,"label":"HL"},{"time":1778716800,"price":748.17,"label":"HH"},{"time":1779148800,"price":733.73,"label":"HL"},{"time":1779753600,"price":750.59,"label":"HH"},{"time":1779840000,"price":750.46,"label":"HL"},{"time":1780358400,"price":759.57,"label":"HH"},{"time":1780444800,"price":754.24,"label":"HL"},{"time":1780531200,"price":757.09,"label":"LH"},{"time":1780617600,"price":735.6548,"label":"HL"},{"time":1780876800,"price":737.3204,"label":"LH"},{"time":1781049600,"price":723.5659,"label":"HL"},{"time":1781481600,"price":752.8904,"label":"LH"},{"time":1781654400,"price":739.056,"label":"HL"},{"time":1781740800,"price":746.74,"label":"LH"},{"time":1782259200,"price":733.24,"label":"HL"},{"time":1782345600,"price":734.3,"label":"LH"},{"time":1782432000,"price":728.99,"label":"HL"}],"pivots2":[{"time":1776729600,"price":429.57,"label":"LL"},{"time":1776816000,"price":435.26,"label":"LH"},{"time":1776902400,"price":431.04,"label":"HL"},{"time":1776988800,"price":433.25,"label":"LH"},{"time":1777420800,"price":417.41,"label":"LL"},{"time":1777507200,"price":423.66,"label":"LH"},{"time":1777852800,"price":414.71,"label":"LL"},{"time":1778457600,"price":434.65,"label":"LH"},{"time":1778803200,"price":417.29,"label":"HL"},{"time":1779062400,"price":418.43,"label":"LH"},{"time":1779148800,"price":411.5,"label":"LL"},{"time":1779235200,"price":417.4,"label":"LH"},{"time":1779408000,"price":413.82,"label":"HL"},{"time":1779753600,"price":414.0,"label":"LH"},{"time":1779840000,"price":408.49,"label":"LL"},{"time":1780012800,"price":417.12,"label":"LH"},{"time":1780272000,"price":411.26,"label":"HL"},{"time":1780358400,"price":411.95,"label":"LH"},{"time":1780444800,"price":407.87,"label":"LL"},{"time":1780531200,"price":411.27,"label":"LH"},{"time":1780617600,"price":396.24,"label":"LL"},{"time":1780876800,"price":397.27,"label":"LH"},{"time":1781049600,"price":374.58,"label":"LL"},{"time":1781568000,"price":397.63,"label":"LH"},{"time":1782259200,"price":365.92,"label":"LL"},{"time":1782432000,"price":373.63,"label":"LH"},{"time":1782691200,"price":368.58,"label":"HL"}]},{"id":"spy-btc","trend1":"LH + HL →","trend2":"LL + LH ↘","signal":"⚖️ Mixed →↘","pivots1":[{"time":1776729600,"price":704.08,"label":"LL"},{"time":1776816000,"price":711.21,"label":"HH"},{"time":1776902400,"price":708.45,"label":"HL"},{"time":1777248000,"price":715.17,"label":"HH"},{"time":1777420800,"price":711.58,"label":"HL"},{"time":1777593600,"price":720.65,"label":"HH"},{"time":1777852800,"price":718.01,"label":"HL"},{"time":1778025600,"price":733.83,"label":"HH"},{"time":1778112000,"price":731.58,"label":"HL"},{"time":1778457600,"price":739.3,"label":"HH"},{"time":1778544000,"price":738.18,"label":"HL"},{"time":1778716800,"price":748.17,"label":"HH"},{"time":1779148800,"price":733.73,"label":"HL"},{"time":1779753600,"price":750.59,"label":"HH"},{"time":1779840000,"price":750.46,"label":"HL"},{"time":1780358400,"price":759.57,"label":"HH"},{"time":1780444800,"price":754.24,"label":"HL"},{"time":1780531200,"price":757.09,"label":"LH"},{"time":1780617600,"price":735.6548,"label":"HL"},{"time":1780876800,"price":737.3204,"label":"LH"},{"time":1781049600,"price":723.5659,"label":"HL"},{"time":1781481600,"price":752.8904,"label":"LH"},{"time":1781654400,"price":739.056,"label":"HL"},{"time":1781740800,"price":746.74,"label":"LH"},{"time":1782259200,"price":733.24,"label":"HL"},{"time":1782345600,"price":734.3,"label":"LH"},{"time":1782432000,"price":728.99,"label":"HL"}],"pivots2":[{"time":1778630400,"price":79277.1172,"label":"LL"},{"time":1778716800,"price":81051.25,"label":"HH"},{"time":1779148800,"price":76750.9062,"label":"LL"},{"time":1779321600,"price":77539.1719,"label":"LH"},{"time":1779408000,"price":75488.2422,"label":"LL"},{"time":1779667200,"price":77279.9297,"label":"LH"},{"time":1780012800,"price":73372.5234,"label":"LL"},{"time":1780099200,"price":73754.8359,"label":"LH"},{"time":1780704000,"price":60867.4141,"label":"LL"},{"time":1780790400,"price":63239.5195,"label":"LH"},{"time":1781049600,"price":61449.2891,"label":"HL"},{"time":1781136000,"price":63561.0547,"label":"LH"},{"time":1781222400,"price":63543.1992,"label":"HL"},{"time":1781481600,"price":66289.5,"label":"LH"},{"time":1781740800,"price":62896.4727,"label":"HL"},{"time":1781913600,"price":64239.6758,"label":"LH"},{"time":1782000000,"price":63237.5391,"label":"HL"},{"time":1782086400,"price":63952.1055,"label":"LH"},{"time":1782345600,"price":59721.6758,"label":"LL"},{"time":1782432000,"price":60016.4297,"label":"LH"},{"time":1782604800,"price":59532.3398,"label":"LL"},{"time":1782691200,"price":60138.3789,"label":"LH"}]}],"summary":{"bearish_count":0,"bullish_count":1,"net_score":1,"label":"BULLISH","details":[{"id":"spy-hyg","label":"SPY ↔ HYG","signal":"ALIGNED →→"},{"id":"spy-qqq","label":"SPY ↔ QQQ","signal":"ALIGNED →→"},{"id":"spy-iwm","label":"SPY ↔ IWM","signal":"⚠️ BULLISH →↗"},{"id":"spy-smh","label":"SPY ↔ SMH","signal":"ALIGNED →→"},{"id":"spy-gld","label":"SPY ↔ GLD","signal":"ALIGNED →→"},{"id":"spy-btc","label":"SPY ↔ BTC","signal":"⚖️ Mixed →↘"}]}}