{
  "generated": "2026-04-28T13:32:04.111493+00:00",
  "day_quality": {
    "grade": "F",
    "modifiers": {
      "atr_above_avg": false,
      "volume_above_20d": false,
      "volume_above_50d": false,
      "prior_day_move_pct": -0.11
    }
  },
  "regime": {
    "label": "Trending",
    "direction": "up",
    "atr_trend": "contracting",
    "index_alignment": "aligned"
  },
  "symbols": {
    "SPY": {
      "date": "2026-04-27",
      "open": 713.17,
      "high": 715.61,
      "low": 712.29,
      "close": 715.17,
      "volume": 32767851,
      "atr_14": 7.68,
      "atr_20d_avg": 9.77,
      "atr_above_avg": false,
      "rsi_14": 70.7,
      "macd_line": -34.048,
      "macd_signal": -24.3781,
      "macd_histogram": -9.6699,
      "ma_20": 685.04,
      "above_ma_20": true,
      "gap_pct": -0.11,
      "gap_type": "down",
      "gap_significant": false,
      "gap_strong": false,
      "outside_day": false,
      "outside_day_direction": "none",
      "patterns": {
        "orb_qualified": false,
        "gap_fill_candidate": false,
        "gap_continuation_candidate": false,
        "outside_day": false
      },
      "engulfing": "none",
      "squeeze": {
        "status": "normal",
        "momentum": -2.0643,
        "momentum_increasing": false
      },
      "vwap": {
        "vwap": 711.27,
        "above_vwap": false,
        "distance_pct": -0.05
      },
      "rsi_divergence": {
        "signal": "none",
        "description": "No divergence"
      },
      "eod_outcome": {
        "orb_high": 714.41,
        "orb_low": 712.6,
        "orb_breached_up": true,
        "orb_breached_down": true,
        "orb_breached": true,
        "orb_direction": "up",
        "orb_hit_t1": false,
        "gap_filled": true,
        "day_range": 3.32,
        "day_range_pct": 0.47,
        "day_atr_multiple": 0.43
      },
      "premarket": {
        "high": 714.43,
        "low": 712.9,
        "close": 713.25
      },
      "last_hour": {
        "high": 715.63,
        "low": 714.88,
        "close": 715.16
      }
    },
    "QQQ": {
      "date": "2026-04-27",
      "open": 663.39,
      "high": 664.42,
      "low": 660.69,
      "close": 664.23,
      "volume": 31899468,
      "atr_14": 10.17,
      "atr_20d_avg": 11.22,
      "atr_above_avg": false,
      "rsi_14": 75.0,
      "macd_line": -41.0829,
      "macd_signal": -28.2589,
      "macd_histogram": -12.824,
      "ma_20": 620.38,
      "above_ma_20": true,
      "gap_pct": -0.07,
      "gap_type": "none",
      "gap_significant": false,
      "gap_strong": false,
      "outside_day": false,
      "outside_day_direction": "none",
      "patterns": {
        "orb_qualified": false,
        "gap_fill_candidate": false,
        "gap_continuation_candidate": false,
        "outside_day": false
      },
      "engulfing": "none",
      "squeeze": {
        "status": "strong",
        "momentum": 2.3484,
        "momentum_increasing": true
      },
      "vwap": {
        "vwap": 656.11,
        "above_vwap": false,
        "distance_pct": -0.08
      },
      "rsi_divergence": {
        "signal": "none",
        "description": "No divergence"
      },
      "eod_outcome": {
        "orb_high": 663.85,
        "orb_low": 660.69,
        "orb_breached_up": true,
        "orb_breached_down": false,
        "orb_breached": true,
        "orb_direction": "up",
        "orb_hit_t1": false,
        "gap_filled": false,
        "day_range": 3.73,
        "day_range_pct": 0.56,
        "day_atr_multiple": 0.37
      },
      "premarket": {
        "high": 665.6,
        "low": 652.75,
        "close": 663.47
      },
      "last_hour": {
        "high": 664.42,
        "low": 663.43,
        "close": 664.27
      }
    },
    "IWM": {
      "date": "2026-04-27",
      "open": 276.82,
      "high": 278.24,
      "low": 276.25,
      "close": 277.14,
      "volume": 22180364,
      "atr_14": 4.43,
      "atr_20d_avg": 5.32,
      "atr_above_avg": false,
      "rsi_14": 69.9,
      "macd_line": -15.7164,
      "macd_signal": -12.2003,
      "macd_histogram": -3.5161,
      "ma_20": 264.2,
      "above_ma_20": true,
      "gap_pct": 0.06,
      "gap_type": "none",
      "gap_significant": false,
      "gap_strong": false,
      "outside_day": false,
      "outside_day_direction": "none",
      "patterns": {
        "orb_qualified": false,
        "gap_fill_candidate": false,
        "gap_continuation_candidate": false,
        "outside_day": false
      },
      "engulfing": "none",
      "squeeze": {
        "status": "normal",
        "momentum": -0.7894,
        "momentum_increasing": true
      },
      "vwap": {
        "vwap": 275.8,
        "above_vwap": false,
        "distance_pct": -0.07
      },
      "rsi_divergence": {
        "signal": "none",
        "description": "No divergence"
      },
      "eod_outcome": {
        "orb_high": 278.24,
        "orb_low": 276.25,
        "orb_breached_up": false,
        "orb_breached_down": false,
        "orb_breached": false,
        "orb_direction": "none",
        "orb_hit_t1": false,
        "gap_filled": false,
        "day_range": 1.99,
        "day_range_pct": 0.72,
        "day_atr_multiple": 0.45
      },
      "premarket": {
        "high": 277.22,
        "low": 276.34,
        "close": 276.39
      },
      "last_hour": {
        "high": 277.16,
        "low": 276.74,
        "close": 277.1
      }
    },
    "SMH": {
      "date": "2026-04-27",
      "open": 509.19,
      "high": 510.09,
      "low": 497.74,
      "close": 506.26,
      "volume": 9005543,
      "atr_14": 12.82,
      "atr_20d_avg": 12.72,
      "atr_above_avg": true,
      "rsi_14": 84.0,
      "macd_line": -52.2638,
      "macd_signal": -37.0168,
      "macd_histogram": -15.2471,
      "ma_20": 439.18,
      "above_ma_20": true,
      "gap_pct": 0.54,
      "gap_type": "up",
      "gap_significant": false,
      "gap_strong": false,
      "outside_day": false,
      "outside_day_direction": "none",
      "patterns": {
        "orb_qualified": false,
        "gap_fill_candidate": false,
        "gap_continuation_candidate": false,
        "outside_day": false
      },
      "engulfing": "none",
      "squeeze": {
        "status": "none",
        "momentum": -13.5848,
        "momentum_increasing": false
      },
      "vwap": {
        "vwap": 486.47,
        "above_vwap": false,
        "distance_pct": -0.19
      },
      "rsi_divergence": {
        "signal": "none",
        "description": "No divergence"
      },
      "eod_outcome": {
        "orb_high": 510.09,
        "orb_low": 498.8,
        "orb_breached_up": false,
        "orb_breached_down": true,
        "orb_breached": true,
        "orb_direction": "down",
        "orb_hit_t1": false,
        "gap_filled": true,
        "day_range": 12.35,
        "day_range_pct": 2.48,
        "day_atr_multiple": 0.96
      },
      "premarket": {
        "high": 515.37,
        "low": 508.46,
        "close": 508.62
      },
      "last_hour": {
        "high": 506.29,
        "low": 504.17,
        "close": 506.19
      }
    },
    "BTC": {
      "date": "2026-04-27",
      "open": 78670.85,
      "high": 79420.27,
      "low": 76579.79,
      "close": 76870.29,
      "volume": 40238612480,
      "atr_14": 2177.27,
      "atr_20d_avg": 2381.49,
      "atr_above_avg": false,
      "rsi_14": 58.0,
      "macd_line": -3406.7802,
      "macd_signal": -3540.5238,
      "macd_histogram": 133.7437,
      "ma_20": 75215.17,
      "above_ma_20": true,
      "gap_pct": 0.02,
      "gap_type": "none",
      "gap_significant": false,
      "gap_strong": false,
      "outside_day": true,
      "outside_day_direction": "down",
      "patterns": {
        "orb_qualified": false,
        "gap_fill_candidate": false,
        "gap_continuation_candidate": false,
        "outside_day": true
      },
      "engulfing": "bearish",
      "squeeze": {
        "status": "weak",
        "momentum": -673.8191,
        "momentum_increasing": false
      },
      "vwap": {
        "vwap": 76262.59,
        "above_vwap": false,
        "distance_pct": -0.27
      },
      "rsi_divergence": {
        "signal": "none",
        "description": "No divergence"
      },
      "eod_outcome": {
        "orb_high": 77948.45,
        "orb_low": 77792.48,
        "orb_breached_up": true,
        "orb_breached_down": true,
        "orb_breached": true,
        "orb_direction": "down",
        "orb_hit_t1": false,
        "gap_filled": false,
        "day_range": 2840.48,
        "day_range_pct": 3.71,
        "day_atr_multiple": 1.3
      },
      "premarket": {
        "high": 77989.4,
        "low": 77565.17,
        "close": 77902.45
      },
      "last_hour": {
        "high": 77838.49,
        "low": 76581.11,
        "close": 76789.54
      }
    },
    "ETH": {
      "date": "2026-04-27",
      "open": 2370.32,
      "high": 2399.44,
      "low": 2269.06,
      "close": 2288.95,
      "volume": 19104159744,
      "atr_14": 85.54,
      "atr_20d_avg": 100.78,
      "atr_above_avg": false,
      "rsi_14": 51.5,
      "macd_line": -69.5862,
      "macd_signal": -102.4883,
      "macd_histogram": 32.9021,
      "ma_20": 2309.27,
      "above_ma_20": false,
      "gap_pct": 0.02,
      "gap_type": "none",
      "gap_significant": false,
      "gap_strong": false,
      "outside_day": true,
      "outside_day_direction": "down",
      "patterns": {
        "orb_qualified": false,
        "gap_fill_candidate": false,
        "gap_continuation_candidate": false,
        "outside_day": true
      },
      "engulfing": "bearish",
      "squeeze": {
        "status": "strong",
        "momentum": -20.7182,
        "momentum_increasing": false
      },
      "vwap": {
        "vwap": 2274.53,
        "above_vwap": false,
        "distance_pct": -0.38
      },
      "rsi_divergence": {
        "signal": "bullish",
        "description": "Price LL, RSI HL"
      },
      "eod_outcome": {
        "orb_high": 2324.18,
        "orb_low": 2318.77,
        "orb_breached_up": true,
        "orb_breached_down": true,
        "orb_breached": true,
        "orb_direction": "down",
        "orb_hit_t1": false,
        "gap_filled": false,
        "day_range": 130.38,
        "day_range_pct": 5.75,
        "day_atr_multiple": 1.52
      },
      "premarket": {
        "high": 2325.36,
        "low": 2309.09,
        "close": 2322.31
      },
      "last_hour": {
        "high": 2315.19,
        "low": 2266.49,
        "close": 2274.82
      }
    },
    "GLD": {
      "date": "2026-04-27",
      "open": 431.66,
      "high": 431.8,
      "low": 428.54,
      "close": 429.89,
      "volume": 6037903,
      "atr_14": 6.95,
      "atr_20d_avg": 10.7,
      "atr_above_avg": false,
      "rsi_14": 45.5,
      "macd_line": -7.8957,
      "macd_signal": -5.8825,
      "macd_histogram": -2.0132,
      "ma_20": 434.46,
      "above_ma_20": false,
      "gap_pct": -0.37,
      "gap_type": "down",
      "gap_significant": false,
      "gap_strong": false,
      "outside_day": false,
      "outside_day_direction": "none",
      "patterns": {
        "orb_qualified": false,
        "gap_fill_candidate": false,
        "gap_continuation_candidate": false,
        "outside_day": false
      },
      "engulfing": "none",
      "squeeze": {
        "status": "strong",
        "momentum": -5.039,
        "momentum_increasing": true
      },
      "vwap": {
        "vwap": 420.12,
        "above_vwap": false,
        "distance_pct": -0.05
      },
      "rsi_divergence": {
        "signal": "bullish",
        "description": "Price LL, RSI HL"
      },
      "eod_outcome": {
        "orb_high": 431.8,
        "orb_low": 430.3,
        "orb_breached_up": false,
        "orb_breached_down": true,
        "orb_breached": true,
        "orb_direction": "down",
        "orb_hit_t1": false,
        "gap_filled": false,
        "day_range": 3.26,
        "day_range_pct": 0.76,
        "day_atr_multiple": 0.47
      },
      "premarket": {
        "high": 433.25,
        "low": 431.05,
        "close": 431.18
      },
      "last_hour": {
        "high": 429.94,
        "low": 429.43,
        "close": 429.87
      }
    },
    "SLV": {
      "date": "2026-04-27",
      "open": 68.3,
      "high": 68.55,
      "low": 67.56,
      "close": 68.33,
      "volume": 12982487,
      "atr_14": 2.44,
      "atr_20d_avg": 3.05,
      "atr_above_avg": false,
      "rsi_14": 47.2,
      "macd_line": -3.1319,
      "macd_signal": -2.1794,
      "macd_histogram": -0.9525,
      "ma_20": 68.8,
      "above_ma_20": false,
      "gap_pct": -0.71,
      "gap_type": "down",
      "gap_significant": false,
      "gap_strong": false,
      "outside_day": false,
      "outside_day_direction": "none",
      "patterns": {
        "orb_qualified": false,
        "gap_fill_candidate": false,
        "gap_continuation_candidate": false,
        "outside_day": false
      },
      "engulfing": "none",
      "squeeze": {
        "status": "none",
        "momentum": -1.7425,
        "momentum_increasing": true
      },
      "vwap": {
        "vwap": 65.61,
        "above_vwap": false,
        "distance_pct": -0.13
      },
      "rsi_divergence": {
        "signal": "none",
        "description": "No divergence"
      },
      "eod_outcome": {
        "orb_high": 68.4,
        "orb_low": 67.88,
        "orb_breached_up": true,
        "orb_breached_down": true,
        "orb_breached": true,
        "orb_direction": "up",
        "orb_hit_t1": false,
        "gap_filled": false,
        "day_range": 0.99,
        "day_range_pct": 1.47,
        "day_atr_multiple": 0.41
      },
      "premarket": {
        "high": 69.52,
        "low": 67.94,
        "close": 68.03
      },
      "last_hour": {
        "high": 68.4,
        "low": 68.25,
        "close": 68.34
      }
    },
    "USO": {
      "date": "2026-04-27",
      "open": 133.96,
      "high": 136.48,
      "low": 133.21,
      "close": 134.72,
      "volume": 6892378,
      "atr_14": 7.48,
      "atr_20d_avg": 8.11,
      "atr_above_avg": false,
      "rsi_14": 60.4,
      "macd_line": 3.2463,
      "macd_signal": -1.3552,
      "macd_histogram": 4.6015,
      "ma_20": 128.5,
      "above_ma_20": true,
      "gap_pct": 1.18,
      "gap_type": "up",
      "gap_significant": true,
      "gap_strong": false,
      "outside_day": false,
      "outside_day_direction": "none",
      "patterns": {
        "orb_qualified": false,
        "gap_fill_candidate": true,
        "gap_continuation_candidate": false,
        "outside_day": false
      },
      "engulfing": "none",
      "squeeze": {
        "status": "none",
        "momentum": 2.8466,
        "momentum_increasing": false
      },
      "vwap": {
        "vwap": 139.17,
        "above_vwap": true,
        "distance_pct": 0.08
      },
      "rsi_divergence": {
        "signal": "none",
        "description": "No divergence"
      },
      "eod_outcome": {
        "orb_high": 134.94,
        "orb_low": 133.21,
        "orb_breached_up": true,
        "orb_breached_down": false,
        "orb_breached": true,
        "orb_direction": "up",
        "orb_hit_t1": false,
        "gap_filled": false,
        "day_range": 3.26,
        "day_range_pct": 2.45,
        "day_atr_multiple": 0.44
      },
      "premarket": {
        "high": 134.9,
        "low": 129.49,
        "close": 134.2
      },
      "last_hour": {
        "high": 135.06,
        "low": 134.11,
        "close": 134.73
      }
    }
  },
  "active_patterns": [
    {
      "symbol": "BTC",
      "pattern": "Engulfing",
      "direction": "down",
      "notes": "Bearish engulfing, vol confirmed",
      "levels": {
        "entry": 76579.79,
        "stop": 79420.27,
        "t1": 73313.89,
        "t2": 72225.25,
        "atr": 2177.27
      },
      "outcome": {
        "next_day": true,
        "note": "Enter below $76579.79 next session"
      }
    },
    {
      "symbol": "BTC",
      "pattern": "Outside Day",
      "direction": "down",
      "notes": "Close lower 25%: 76870.29 (H 79420.27 / L 76579.79)",
      "levels": {
        "entry": 76579.79,
        "stop": 79420.27,
        "t1": 72319.06,
        "range_size": 2840.48,
        "atr": 2177.27
      },
      "outcome": {
        "next_day": true,
        "note": "Enter below $76579.79 next session"
      }
    },
    {
      "symbol": "ETH",
      "pattern": "Engulfing",
      "direction": "down",
      "notes": "Bearish engulfing, vol confirmed",
      "levels": {
        "entry": 2269.06,
        "stop": 2399.44,
        "t1": 2140.75,
        "t2": 2097.98,
        "atr": 85.54
      },
      "outcome": {
        "next_day": true,
        "note": "Enter below $2269.06 next session"
      }
    },
    {
      "symbol": "ETH",
      "pattern": "Outside Day",
      "direction": "down",
      "notes": "Close lower 25%: 2288.95 (H 2399.44 / L 2269.06)",
      "levels": {
        "entry": 2269.06,
        "stop": 2399.44,
        "t1": 2073.49,
        "range_size": 130.38,
        "atr": 85.54
      },
      "outcome": {
        "next_day": true,
        "note": "Enter below $2269.06 next session"
      }
    }
  ],
  "windows": {
    "premarket": {
      "from": "08:00",
      "to": "09:00"
    },
    "opening_range": {
      "from": "09:30",
      "to": "09:30"
    },
    "session": {
      "from": "09:30",
      "to": "15:30"
    },
    "last_hour": {
      "from": "15:30",
      "to": "15:30"
    }
  }
}